orion_cli/__init__.py
orion_cli/__main__.py
orion_cli/cli.py
orion_cli/helpers/asset_helper.py
orion_cli/helpers/cad_helper.py
orion_cli/helpers/config_helper.py
orion_cli/helpers/numpy_helper.py
orion_cli/helpers/remote_helper.py
orion_cli/services/__init__.py
orion_cli/services/base_service.py
orion_cli/services/cad_service.py
orion_cli/services/create_service.py
orion_cli/services/deploy_service.py
orion_cli/services/display_service.py
orion_cli/services/log_service.py
orion_cli/services/revision_service.py
orion_cli/templates/README_template.py
orion_cli/templates/gitignore_template.py
orion_cli-0.1.2.dist-info/METADATA
orion_cli-0.1.2.dist-info/WHEEL
orion_cli-0.1.2.dist-info/entry_points.txt
orion_cli-0.1.2.dist-info/RECORD
