Metadata-Version: 2.1
Name: orion-cli
Version: 0.1.2
Summary: Command-line tool for Open Orion PLM
License: Apache-2.0
Author: Afshawn Lotfi
Author-email: afshawn@openorion.org
Requires-Python: >=3.10,<3.12
Classifier: License :: OSI Approved :: Apache Software License
Classifier: Programming Language :: Python :: 3
Classifier: Programming Language :: Python :: 3.10
Classifier: Programming Language :: Python :: 3.11
Requires-Dist: cadquery (>=2.4.0,<3.0.0) ; platform_machine != "arm64"
Requires-Dist: cadquery-arm ; sys_platform == "darwin" and platform_machine == "arm64"
Requires-Dist: click (>=8.0,<9.0)
Requires-Dist: jupyter-cadquery-orion (>=0.0.1,<0.0.2)
Requires-Dist: lxml-html-clean (>=0.1.1,<0.2.0)
Requires-Dist: numpy (<2.0.0)
Requires-Dist: ocp-tessellate-orion (>=0.0.1,<0.0.2)
Requires-Dist: pandas (>=2.2.2,<3.0.0)
Requires-Dist: pydantic (>=2.8.2,<3.0.0)
Requires-Dist: pygithub (>=2.3.0,<3.0.0)
Requires-Dist: pyyaml (>=6.0.1,<7.0.0)
Requires-Dist: requests (>=2.32.3,<3.0.0)
Requires-Dist: scipy (>=1.14.0,<2.0.0)
Requires-Dist: tabulate (>=0.9.0,<0.10.0)
